simplelog/__init__.py
simplelog/tests/__init__.py
simplelog/tests/tasks.py
simplelog/tests/test_basic.py
simplelog/tests/test_json_format_basic.py
simplelog/tests/test_json_formatter_set_level.py
simplelog/tests/test_set_level.py
simplelog/utils/__init__.py
simplelog/utils/defaults.py
simplelog/utils/json_log_formatter.py
simplelog/utils/logger.py
pysimple_log-0.0.5.dist-info/METADATA
pysimple_log-0.0.5.dist-info/WHEEL
pysimple_log-0.0.5.dist-info/top_level.txt
pysimple_log-0.0.5.dist-info/RECORD
