Metadata-Version: 2.1
Name: pysimple-log
Version: 0.0.5
Summary: simple log configuration
Home-page: https://github.com/changyubiao/pysimple-log.git
Author: frank
Author-email: 15769162764@163.com
License: Apache License 2.0
Project-URL: Code, https://github.com/changyubiao/pysimple-log.git
Platform: UNKNOWN
Classifier: Development Status :: 5 - Production/Stable
Classifier: Topic :: System :: Logging
Classifier: Intended Audience :: Developers
Classifier: Natural Language :: English
Classifier: License :: OSI Approved :: MIT License
Classifier: Operating System :: OS Independent
Classifier: Programming Language :: Python
Classifier: Programming Language :: Python :: 3
Classifier: Programming Language :: Python :: 3.5
Classifier: Programming Language :: Python :: 3.6
Classifier: Programming Language :: Python :: 3.7
Classifier: Programming Language :: Python :: 3.8
Classifier: Programming Language :: Python :: 3 :: Only
Classifier: Programming Language :: Python :: Implementation :: PyPy
Classifier: Programming Language :: Python :: Implementation :: CPython
Requires-Python: >=3.0
Requires-Dist: concurrent-log-handler (>=0.9.16)
